pyflatten/__init__.py
pyflatten-1.0.1.dist-info/DESCRIPTION.rst
pyflatten-1.0.1.dist-info/METADATA
pyflatten-1.0.1.dist-info/RECORD
pyflatten-1.0.1.dist-info/WHEEL
pyflatten-1.0.1.dist-info/metadata.json
pyflatten-1.0.1.dist-info/top_level.txt
