Metadata-Version: 2.0
Name: pyflatten
Version: 1.0.1
Summary: A utility for flattening nested data structures.
Home-page: https://github.com/ericmjl/pyflatten
Author: Eric J. Ma
Author-email: ericmajinglong@gmail.com
License: MIT
Platform: UNKNOWN
